py2deb/__init__.py
py2deb/cli.py
py2deb/converter.py
py2deb/hooks.py
py2deb/namespaces.py
py2deb/package.py
py2deb/tests.py
py2deb/utils.py
py2deb-5.0.dist-info/LICENSE.txt
py2deb-5.0.dist-info/METADATA
py2deb-5.0.dist-info/WHEEL
py2deb-5.0.dist-info/entry_points.txt
py2deb-5.0.dist-info/top_level.txt
py2deb-5.0.dist-info/RECORD
