Metadata-Version: 2.1
Name: py2deb
Version: 5.0
Summary: Python to Debian package converter
Home-page: https://py2deb.readthedocs.io
Author: Peter Odding & Arjan Verwer (Paylogic International)
Author-email: peter.odding@paylogic.com
License: MIT
Platform: UNKNOWN
Classifier: Development Status :: 5 - Production/Stable
Classifier: Intended Audience :: Developers
Classifier: Intended Audience :: Information Technology
Classifier: Intended Audience :: System Administrators
Classifier: License :: OSI Approved :: MIT License
Classifier: Operating System :: POSIX :: Linux
Classifier: Programming Language :: Python
Classifier: Programming Language :: Python :: 2
Classifier: Programming Language :: Python :: 2.7
Classifier: Programming Language :: Python :: 3
Classifier: Programming Language :: Python :: 3.5
Classifier: Programming Language :: Python :: 3.6
Classifier: Programming Language :: Python :: 3.7
Classifier: Programming Language :: Python :: Implementation :: CPython
Classifier: Programming Language :: Python :: Implementation :: PyPy
Classifier: Topic :: Software Development :: Build Tools
Classifier: Topic :: Software Development :: Libraries :: Python Modules
Classifier: Topic :: System :: Archiving :: Packaging
Classifier: Topic :: System :: Installation/Setup
Classifier: Topic :: System :: Software Distribution
Classifier: Topic :: System :: Systems Administration
Classifier: Topic :: Utilities
Requires-Python: >=2.7, !=3.0.*, !=3.1.*, !=3.2.*, !=3.3.*, !=3.4.*
Requires-Dist: coloredlogs (>=0.5)
Requires-Dist: deb-pkg-tools (>=5.2)
Requires-Dist: executor (>=21.0)
Requires-Dist: humanfriendly (>=8.0)
Requires-Dist: pip-accel (<=0.43,>=0.25)
Requires-Dist: pkginfo (>=1.1)
Requires-Dist: property-manager (>=2.3.1)
Requires-Dist: six (>=1.6.1)
Requires-Dist: importlib ; python_version == "2.6" or python_version == "3.0"
